goekendatascience/__init__.py
goekendatascience/goekendatascience.py
goekendatascience-0.1.26.dist-info/licenses/LICENSE.txt
goekendatascience-0.1.26.dist-info/METADATA
goekendatascience-0.1.26.dist-info/WHEEL
goekendatascience-0.1.26.dist-info/top_level.txt
goekendatascience-0.1.26.dist-info/RECORD
